model_observer/__init__.py
model_observer/model.py
model_observer-0.0.22.dist-info/LICENSE
model_observer-0.0.22.dist-info/METADATA
model_observer-0.0.22.dist-info/WHEEL
model_observer-0.0.22.dist-info/top_level.txt
model_observer-0.0.22.dist-info/RECORD
