Metadata-Version: 2.1
Name: model-observer
Version: 0.0.22
Summary: Model Observer is a Django package that provides functionality to track events of the model. Based on django signals.
Home-page: https://github.com/ebs-integrator/model-observer
Author: Victor Elceaninov & Dorin Musteata
Author-email: victor.elceaninov@ebs-integrator.org, dorin.musteata@ebs-integrator.org
License: UNKNOWN
Project-URL: Bug Tracker, https://github.com/ebs-integrator/model-observer/issues
Platform: UNKNOWN
Classifier: Programming Language :: Python :: 3
Classifier: Programming Language :: Python :: 3.6
Classifier: Programming Language :: Python :: 3.7
Classifier: Programming Language :: Python :: 3.8
Classifier: Programming Language :: Python :: 3.9
Classifier: License :: OSI Approved :: MIT License
Classifier: Operating System :: OS Independent
Requires-Python: >=3.6
